{
  "GOOGL": {
    "mode": "SIMULATED",
    "symbol": "GOOGL",
    "session": 48,
    "iteration": 0,
    "timestamp": "2026-03-04T04:30:44.603378+00:00",
    "bid": 303.615,
    "ask": 303.625,
    "signal": "HOLD",
    "regime": "NEUTRAL",
    "rsi": 50,
    "ema_fast": 0,
    "ema_slow": 0,
    "ema_200": 0,
    "macd_hist": 0,
    "vwap": 0,
    "atr": 0,
    "confirmations": [],
    "initial_cash": 10000.0,
    "available_cash": 10000.0,
    "settlement": 0,
    "win_rate": 0.0,
    "total_trades": 0,
    "winning_trades": 0,
    "gross_profit": 0.0,
    "gross_loss": 0.0,
    "total_fees": 0.0,
    "total_slippage": 0.0,
    "total_sim_trades": 193,
    "total_sim_wins": 54,
    "total_sim_pnl": 134.53119850000007,
    "position": null,
    "trades": [],
    "candles": [],
    "status": "completed",
    "next_scan_in": 0,
    "is_waiting": false,
    "mock_time_930": false,
    "blocks": [],
    "sim_start": "2026-02-17",
    "sim_end": "2026-03-03"
  },
  "_main": {
    "mode": "SIMULATED",
    "symbol": "GOOGL",
    "session": 48,
    "iteration": 0,
    "timestamp": "2026-03-04T04:30:44.603378+00:00",
    "bid": 303.615,
    "ask": 303.625,
    "signal": "HOLD",
    "regime": "NEUTRAL",
    "rsi": 50,
    "ema_fast": 0,
    "ema_slow": 0,
    "ema_200": 0,
    "macd_hist": 0,
    "vwap": 0,
    "atr": 0,
    "confirmations": [],
    "initial_cash": 10000.0,
    "available_cash": 10000.0,
    "settlement": 0,
    "win_rate": 0.0,
    "total_trades": 0,
    "winning_trades": 0,
    "gross_profit": 0.0,
    "gross_loss": 0.0,
    "total_fees": 0.0,
    "total_slippage": 0.0,
    "total_sim_trades": 193,
    "total_sim_wins": 54,
    "total_sim_pnl": 134.53119850000007,
    "position": null,
    "trades": [],
    "candles": [],
    "status": "completed",
    "next_scan_in": 0,
    "is_waiting": false,
    "mock_time_930": false,
    "blocks": [],
    "sim_start": "2026-02-17",
    "sim_end": "2026-03-03"
  }
}